shopipy/__init__.py
shopipy/base.py
shopipy/exceptions.py
shopipy/resources/__init__.py
shopipy/resources/collections/__init__.py
shopipy/resources/collections/schemas.py
shopipy/resources/common/__init__.py
shopipy/resources/common/schemas.py
shopipy/resources/customers/__init__.py
shopipy/resources/customers/schemas.py
shopipy/resources/fulfillment/__init__.py
shopipy/resources/fulfillment/schemas.py
shopipy/resources/inventory/__init__.py
shopipy/resources/inventory/schemas.py
shopipy/resources/oauth/__init__.py
shopipy/resources/orders/__init__.py
shopipy/resources/orders/schemas.py
shopipy/resources/products/__init__.py
shopipy/resources/products/schemas.py
shopipy/resources/shipping/__init__.py
shopipy/resources/shipping/schemas.py
shopipy/resources/transactions/__init__.py
shopipy/resources/transactions/schemas.py
shopipy/resources/webhooks/__init__.py
shopipy/resources/webhooks/schemas.py
shopipy/resources/webhooks/topics.py
shopipy-0.4.0.dist-info/LICENSE
shopipy-0.4.0.dist-info/WHEEL
shopipy-0.4.0.dist-info/METADATA
shopipy-0.4.0.dist-info/RECORD
